README.rst
setup.py
voms_auth_system_openstack/__init__.py
voms_auth_system_openstack/plugin.py
voms_auth_system_openstack.egg-info/PKG-INFO
voms_auth_system_openstack.egg-info/SOURCES.txt
voms_auth_system_openstack.egg-info/dependency_links.txt
voms_auth_system_openstack.egg-info/entry_points.txt
voms_auth_system_openstack.egg-info/not-zip-safe
voms_auth_system_openstack.egg-info/top_level.txt