Metadata-Version: 1.1
Name: voms-auth-system-openstack
Version: 1.1
Summary: VOMS-based authentication for Openstack
Home-page: https://github.com/IFCA/voms-auth-system-openstack
Author: Alvaro Lopez
Author-email: aloga@ifca.unican.es
License: Apache License, Version 2.0
Download-URL: https://github.com/IFCA/voms-auth-system-openstack/archive/master.tar.gz
Platform: UNKNOWN
Classifier: Development Status :: 5 - Production/Stable
Classifier: Environment :: Console
Classifier: Intended Audience :: Developers
Classifier: Intended Audience :: Information Technology
Classifier: License :: OSI Approved :: Apache Software License
Classifier: Operating System :: OS Independent
Classifier: Programming Language :: Python
